zebe/config/__init__.py
zebe/config/constant.py
zebe/config/db.py
zebe/modle/__init__.py
zebe/modle/entity/__init__.py
zebe/modle/entity/ad.py
zebe/modle/entity/app.py
zebe/modle/entity/blog.py
zebe/modle/entity/cdrvba.py
zebe/modle/entity/diary.py
zebe/modle/entity/english.py
zebe/modle/entity/memcard.py
zebe/modle/entity/memory.py
zebe/modle/entity/project.py
zebe/modle/entity/remind.py
zebe/modle/entity/wechat.py
zebe/modle/vo/__init__.py
zebe/service/__init__.py
zebe/service/ad.py
zebe/service/app.py
zebe/service/base.py
zebe/service/blog.py
zebe/service/cdrvba.py
zebe/service/diary.py
zebe/service/english.py
zebe/service/memcard.py
zebe/service/memory.py
zebe/service/project.py
zebe/service/remind.py
zebe/service/wechat.py
zebe_data_service-1.7.0.dist-info/LICENSE.txt
zebe_data_service-1.7.0.dist-info/METADATA
zebe_data_service-1.7.0.dist-info/RECORD
zebe_data_service-1.7.0.dist-info/WHEEL
zebe_data_service-1.7.0.dist-info/top_level.txt
